LICENSE
MANIFEST.in
README.md
pyproject.toml
spsdk_offline_signature_provider/__init__.py
spsdk_offline_signature_provider/offline_signature_provider.py
spsdk_offline_signature_provider.egg-info/PKG-INFO
spsdk_offline_signature_provider.egg-info/SOURCES.txt
spsdk_offline_signature_provider.egg-info/dependency_links.txt
spsdk_offline_signature_provider.egg-info/entry_points.txt
spsdk_offline_signature_provider.egg-info/requires.txt
spsdk_offline_signature_provider.egg-info/top_level.txt
tests/__init__.py
tests/test_offline_signature_provider.py